{
  "account_id": "RRR_005",
  "company_name": "Rapid Response Restoration",
  "business_hours": {
    "days": "Monday-Friday",
    "start": "8:00 AM",
    "end": "6:00 PM",
    "timezone": "Eastern"
  },
  "office_address": "Expanded to serve Charlotte, NC",
  "services_supported": [
    "water damage",
    "fire damage",
    "mold remediation"
  ],
  "emergency_definition": [
    "active flooding or water intrusion",
    "sewage backup",
    "fire or smoke damage within the last 24 hours",
    "mold in HVAC systems",
    "biohazard cleanup requests"
  ],
  "emergency_routing_rules": {
    "step_1": {
      "contact_name": "dispatch",
      "phone": "404-555-0600 (Atlanta) or 704-555-0700 (Charlotte)",
      "rings_before_next": 2
    },
    "step_2": {
      "contact_name": "Jerome",
      "phone": "404-555-0612",
      "rings_before_next": null
    },
    "fallback": "never leave the caller without a resolution"
  },
  "non_emergency_routing_rules": "take detailed info and call back within 2 hours",
  "call_transfer_rules": {
    "office_hours_transfer_to": null,
    "timeout_rings": null,
    "if_no_answer": null,
    "collect_before_transfer": [
      "name",
      "number",
      "address",
      "type of damage",
      "when it happened",
      "if there's standing water currently"
    ]
  },
  "integration_constraints": [
    "Xactimate",
    "RMS",
    "Encircle"
  ],
  "after_hours_flow_summary": "Take detailed info and call back within 2 hours for non-emergencies, route emergencies to dispatch line",
  "office_hours_flow_summary": "Office team available to handle calls during business hours",
  "special_rules": [
    "flag if caller mentions insurance",
    "note if rental property",
    "flag if property is vacant or abandoned"
  ],
  "questions_or_unknowns": [],
  "greeting": "Rapid Response Restoration, serving Atlanta and Charlotte.",
  "notes": "Rapid Response Restoration handles water damage, fire damage, and mold remediation in the Atlanta metro area",
  "_meta": {
    "version": "v2",
    "created_at": "2026-03-04T22:35:42.365620",
    "updated_at": "2026-03-04T22:39:03.130041",
    "source": "onboarding_call",
    "pipeline": "pipeline_b"
  },
  "v1_to_v2_changes": {
    "office_address": "Expanded to serve Charlotte, NC",
    "emergency_routing_rules.step_1.phone": "404-555-0600 (Atlanta) or 704-555-0700 (Charlotte)",
    "emergency_definition": [
      "biohazard cleanup requests"
    ],
    "integration_constraints": [
      "Encircle"
    ],
    "special_rules": [
      "flag if property is vacant or abandoned"
    ],
    "greeting": "Rapid Response Restoration, serving Atlanta and Charlotte.",
    "summary": "Rapid Response Restoration expanded to serve Charlotte, NC, and updated emergency routing, definitions, and special rules to accommodate the new market and services."
  },
  "new_rules_added": [
    "Ask for city and zip code early in the call to determine market",
    "If caller says FEMA or federal disaster declaration, escalate to Jerome directly",
    "If caller says property is vacant or abandoned, flag as different liability situation"
  ]
}